pytest_autoprofile/__init__.py
pytest_autoprofile/_doctest.py
pytest_autoprofile/_json.py
pytest_autoprofile/_multiprocessing.py
pytest_autoprofile/_test_util_capture_warnings.py
pytest_autoprofile/_test_utils.py
pytest_autoprofile/_typing.py
pytest_autoprofile/_warnings.py
pytest_autoprofile/_xdoctest.py
pytest_autoprofile/importers.py
pytest_autoprofile/option_hooks.py
pytest_autoprofile/plugin.py
pytest_autoprofile/profiler.py
pytest_autoprofile/rewriting.py
pytest_autoprofile/setup.py
pytest_autoprofile/startup_hook.py
pytest_autoprofile/utils.py
pytest_autoprofile-0.19.0.dist-info/licenses/LICENCE.txt
pytest_autoprofile-0.19.0.dist-info/METADATA
pytest_autoprofile-0.19.0.dist-info/WHEEL
pytest_autoprofile-0.19.0.dist-info/entry_points.txt
pytest_autoprofile-0.19.0.dist-info/top_level.txt
pytest_autoprofile-0.19.0.dist-info/RECORD
