Metadata-Version: 2.4
Name: pytest-autoprofile
Version: 0.19.0
Summary: `line_profiler.autoprofile`-ing your `pytest` test suite
Author-email: "Terence S.-C. Tsang" <t.tsang.sci@gmail.com>
Project-URL: repository, https://gitlab.com/TTsangSC/pytest-autoprofile
Keywords: testing,profiling,pytest,line_profiler
Classifier: Development Status :: 4 - Beta
Classifier: Environment :: Console
Classifier: Topic :: Software Development :: Testing
Classifier: Operating System :: OS Independent
Classifier: Framework :: Pytest
Classifier: License :: OSI Approved :: MIT License
Classifier: Programming Language :: Python :: 3.8
Classifier: Programming Language :: Python :: 3.9
Classifier: Programming Language :: Python :: 3.10
Classifier: Programming Language :: Python :: 3.11
Classifier: Programming Language :: Python :: 3.12
Classifier: Programming Language :: Python :: 3.13
Classifier: Programming Language :: Python :: 3.14
Requires-Python: >=3.8
License-File: LICENCE.txt
Requires-Dist: exceptiongroup; python_version < "3.11"
Requires-Dist: typing-extensions>=4.10; python_version < "3.13"
Requires-Dist: line_profiler>=5.0
Requires-Dist: pytest>=7.0
Requires-Dist: pluggy>=1.2
Provides-Extra: dev
Requires-Dist: flake8; extra == "dev"
Requires-Dist: mypy; extra == "dev"
Requires-Dist: pytest-doctestplus>=0.10.0; extra == "dev"
Requires-Dist: xdoctest>=0.12.0; extra == "dev"
Requires-Dist: pyyaml; extra == "dev"
Requires-Dist: types-pyyaml; extra == "dev"
Dynamic: license-file
